postfixcalc/__init__.py
postfixcalc/add_math_logic_operators.py
postfixcalc/avaliable_math_logic_operators.py
postfixcalc/exp_tokenization.py
postfixcalc/postfix4tokens.py
postfixcalc/postfix_tokens_calculation.py
postfixcalc_advanced/__init__.py
postfixcalc_advanced/add_math_logic_operators.py
postfixcalc_advanced/avaliable_math_logic_operators.py
postfixcalc_advanced/exp_tokenization.py
postfixcalc_advanced/postfix4tokens.py
postfixcalc_advanced/postfix_tokens_calculation.py
postfixcalc_advanced-0.1.dist-info/METADATA
postfixcalc_advanced-0.1.dist-info/WHEEL
postfixcalc_advanced-0.1.dist-info/top_level.txt
postfixcalc_advanced-0.1.dist-info/RECORD
