Metadata-Version: 2.1
Name: postfixcalc-advanced
Version: 0.1
Summary: Tokeniztion, posfixing and postfix calculation
Home-page: https://github.com/wolkolak/postfixcalc
Author: wolkolak1
Author-email: e.a.z.y.machining@gmail.com
Keywords: python algorithm postfix calculation
Classifier: Development Status :: 3 - Alpha
Classifier: Programming Language :: Python
Classifier: License :: OSI Approved :: MIT License
Classifier: Intended Audience :: Developers
Classifier: Topic :: Software Development :: Build Tools
Classifier: Operating System :: OS Independent
Requires-Dist: requests >=0.0
